pylint_import_requirements/__init__.py
pylint_import_requirements-2.0.5.dist-info/LICENSE
pylint_import_requirements-2.0.5.dist-info/METADATA
pylint_import_requirements-2.0.5.dist-info/WHEEL
pylint_import_requirements-2.0.5.dist-info/top_level.txt
pylint_import_requirements-2.0.5.dist-info/RECORD
