Metadata-Version: 2.1
Name: pylint-import-requirements
Version: 2.0.5
Summary: A pylint plugin to check that all imports have matching requirements specified
Home-page: http://github.com/WanzenBug/pylint-import-requirements
Author: Moritz 'WanzenBug' Wanzenböck
Author-email: moritz@wanzenbug.xyz
License: GPL
Keywords: pylint import requirements
Platform: UNKNOWN
Classifier: Development Status :: 4 - Beta
Classifier: License :: OSI Approved :: GNU General Public License (GPL)
Classifier: Programming Language :: Python :: 3.4
Classifier: Programming Language :: Python :: 3.5
Classifier: Programming Language :: Python :: 3.6
Classifier: Programming Language :: Python :: 3.7
Classifier: Programming Language :: Python :: 3.8
Classifier: Topic :: Software Development :: Debuggers
Classifier: Topic :: Software Development :: Quality Assurance
Classifier: Topic :: Software Development :: Testing
Requires-Dist: astroid
Requires-Dist: importlib-metadata
Requires-Dist: isort
Requires-Dist: pylint
Requires-Dist: setuptools
